{
  "version": "1.0",
  "enabled": true,
  "strict_default": true,
  "checks": [
    {
      "id": "attestation_exchange",
      "description": "Attested identity exchange protocol active"
    },
    {
      "id": "bounded_capability_grants",
      "description": "Capability sharing bounded by reversible contracts"
    },
    {
      "id": "session_merge_controls",
      "description": "Session-bound merge controls with revocation ready"
    },
    {
      "id": "federation_receipts",
      "description": "Full federation receipts emitted for audit"
    }
  ],
  "paths": {
    "state_path": "state/continuity/inter_protheus_federation_trust_web/state.json",
    "latest_path": "state/continuity/inter_protheus_federation_trust_web/latest.json",
    "receipts_path": "state/continuity/inter_protheus_federation_trust_web/receipts.jsonl",
    "history_path": "state/continuity/inter_protheus_federation_trust_web/history.jsonl"
  }
}
